sanic_sessions/__init__.py
sanic_sessions/aioredis.py
sanic_sessions/base.py
sanic_sessions/memcache.py
sanic_sessions/memory.py
sanic_sessions/mongodb.py
sanic_sessions/redis.py
sanic_sessions/utils.py
sanic_sessions-0.9.0.dist-info/licenses/LICENSE
sanic_sessions-0.9.0.dist-info/METADATA
sanic_sessions-0.9.0.dist-info/WHEEL
sanic_sessions-0.9.0.dist-info/top_level.txt
sanic_sessions-0.9.0.dist-info/RECORD
